arffutils/__init__.py
arffutils/arffutils.py
arffutils-0.1.1.dist-info/licenses/LICENSE
arffutils-0.1.1.dist-info/METADATA
arffutils-0.1.1.dist-info/WHEEL
arffutils-0.1.1.dist-info/top_level.txt
arffutils-0.1.1.dist-info/RECORD
