Metadata-Version: 2.4
Name: arffutils
Version: 0.1.1
Summary: Python library to convert from and to ARFF files
Author: thdiaman
License-Expression: MIT
Project-URL: Homepage, https://github.com/thdiaman/arffutils
Project-URL: Issues, https://github.com/thdiaman/arffutils/issues
Keywords: arff,arffutils,weka,dataformat
Classifier: Development Status :: 4 - Beta
Classifier: Intended Audience :: Developers
Classifier: Topic :: Software Development :: Libraries
Classifier: Programming Language :: Python :: 3
Classifier: Programming Language :: Python :: 3 :: Only
Requires-Python: >=3.7
License-File: LICENSE
Requires-Dist: pandas>=1.5.0
Dynamic: license-file
